Metadata-Version: 2.1
Name: jspp
Version: 0.1.8
Summary: BETA
Home-page: https://github.com/JhinScripter/jspp
License: UNKNOWN
Platform: UNKNOWN
Classifier: Programming Language :: Python :: 3
Requires-Python: >=3.6
